streamdeck_uinput/__init__.py
streamdeck_uinput/uinput.c
streamdeck_uinput/uinput.py
streamdeck_uinput/_uinput.cpython-311-x86_64-linux-gnu.so
streamdeck_uinput-0.1.1.dist-info/METADATA
streamdeck_uinput-0.1.1.dist-info/WHEEL
streamdeck_uinput-0.1.1.dist-info/RECORD
