Metadata-Version: 2.1
Name: streamdeck_uinput
Version: 0.1.1
Summary: Basic implementation of UInput for the Elgato Stream Deck
Author: Julian reyes Escrigas
Author-email: julian.reyes.escrigas@gmail.com
Requires-Python: >=3.11,<4.0
Classifier: Programming Language :: Python :: 3
Classifier: Programming Language :: Python :: 3.11
Classifier: Programming Language :: Python :: 3.12
Requires-Dist: evdev (>=1.6.1,<2.0.0)
